{"commitInfo":{"timestamp":1754807051331,"operation":"WRITE","operationParameters":{"mode":"Overwrite","partitionBy":"[]"},"readVersion":9,"isolationLevel":"Serializable","isBlindAppend":false,"operationMetrics":{"numFiles":"7","numOutputRows":"6","numOutputBytes":"11929"},"engineInfo":"Apache-Spark/3.4.4 Delta-Lake/2.4.0","txnId":"8b34c9fd-a36f-4f05-b989-98b8471044cb"}}
{"add":{"path":"part-00001-e10be593-3ae2-4d68-9588-82c8d40ded33-c000.snappy.parquet","partitionValues":{},"size":1857,"modificationTime":1754807049503,"dataChange":true,"stats":"{\"numRecords\":1,\"minValues\":{\"account_id\":\"ACC001\",\"user_id\":\"USER001\",\"account_type\":\"PREMIUM\",\"status\":\"ACTIVE\",\"opened_at\":\"2023-01-15\",\"credit_limit\":10000},\"maxValues\":{\"account_id\":\"ACC001\",\"user_id\":\"USER001\",\"account_type\":\"PREMIUM\",\"status\":\"ACTIVE\",\"opened_at\":\"2023-01-15\",\"credit_limit\":10000},\"nullCount\":{\"account_id\":0,\"user_id\":0,\"account_type\":0,\"status\":0,\"opened_at\":0,\"credit_limit\":0}}"}}
{"add":{"path":"part-00003-c4c3865f-43e6-405b-9bf6-6bf8f6f57a6f-c000.snappy.parquet","partitionValues":{},"size":1865,"modificationTime":1754807049503,"dataChange":true,"stats":"{\"numRecords\":1,\"minValues\":{\"account_id\":\"ACC002\",\"user_id\":\"USER002\",\"account_type\":\"STANDARD\",\"status\":\"ACTIVE\",\"opened_at\":\"2023-02-20\",\"credit_limit\":5000},\"maxValues\":{\"account_id\":\"ACC002\",\"user_id\":\"USER002\",\"account_type\":\"STANDARD\",\"status\":\"ACTIVE\",\"opened_at\":\"2023-02-20\",\"credit_limit\":5000},\"nullCount\":{\"account_id\":0,\"user_id\":0,\"account_type\":0,\"status\":0,\"opened_at\":0,\"credit_limit\":0}}"}}
{"add":{"path":"part-00005-0ae2d9f4-17df-4ed6-beac-6973fe87bcb6-c000.snappy.parquet","partitionValues":{},"size":1872,"modificationTime":1754807049503,"dataChange":true,"stats":"{\"numRecords\":1,\"minValues\":{\"account_id\":\"ACC003\",\"user_id\":\"USER003\",\"account_type\":\"PREMIUM\",\"status\":\"INACTIVE\",\"opened_at\":\"2023-03-10\",\"credit_limit\":15000},\"maxValues\":{\"account_id\":\"ACC003\",\"user_id\":\"USER003\",\"account_type\":\"PREMIUM\",\"status\":\"INACTIVE\",\"opened_at\":\"2023-03-10\",\"credit_limit\":15000},\"nullCount\":{\"account_id\":0,\"user_id\":0,\"account_type\":0,\"status\":0,\"opened_at\":0,\"credit_limit\":0}}"}}
{"add":{"path":"part-00007-18fafbf4-2543-4bd1-b35f-8e9de3c357ef-c000.snappy.parquet","partitionValues":{},"size":1837,"modificationTime":1754807049503,"dataChange":true,"stats":"{\"numRecords\":1,\"minValues\":{\"account_id\":\"ACC004\",\"user_id\":\"USER004\",\"account_type\":\"GOLD\",\"status\":\"ACTIVE\",\"opened_at\":\"2023-04-05\",\"credit_limit\":25000},\"maxValues\":{\"account_id\":\"ACC004\",\"user_id\":\"USER004\",\"account_type\":\"GOLD\",\"status\":\"ACTIVE\",\"opened_at\":\"2023-04-05\",\"credit_limit\":25000},\"nullCount\":{\"account_id\":0,\"user_id\":0,\"account_type\":0,\"status\":0,\"opened_at\":0,\"credit_limit\":0}}"}}
{"add":{"path":"part-00009-bc9f95da-63ff-431c-a65c-2114c807214e-c000.snappy.parquet","partitionValues":{},"size":1865,"modificationTime":1754807049503,"dataChange":true,"stats":"{\"numRecords\":1,\"minValues\":{\"account_id\":\"ACC005\",\"user_id\":\"USER005\",\"account_type\":\"STANDARD\",\"status\":\"ACTIVE\",\"opened_at\":\"2023-05-12\",\"credit_limit\":3000},\"maxValues\":{\"account_id\":\"ACC005\",\"user_id\":\"USER005\",\"account_type\":\"STANDARD\",\"status\":\"ACTIVE\",\"opened_at\":\"2023-05-12\",\"credit_limit\":3000},\"nullCount\":{\"account_id\":0,\"user_id\":0,\"account_type\":0,\"status\":0,\"opened_at\":0,\"credit_limit\":0}}"}}
{"add":{"path":"part-00011-2ebe7e74-4ac7-4e5b-b225-e4cd696c4410-c000.snappy.parquet","partitionValues":{},"size":1858,"modificationTime":1754807049503,"dataChange":true,"stats":"{\"numRecords\":1,\"minValues\":{\"account_id\":\"ACC006\",\"user_id\":\"USER006\",\"account_type\":\"GOLD\",\"status\":\"SUSPENDED\",\"opened_at\":\"2023-06-01\",\"credit_limit\":20000},\"maxValues\":{\"account_id\":\"ACC006\",\"user_id\":\"USER006\",\"account_type\":\"GOLD\",\"status\":\"SUSPENDED\",\"opened_at\":\"2023-06-01\",\"credit_limit\":20000},\"nullCount\":{\"account_id\":0,\"user_id\":0,\"account_type\":0,\"status\":0,\"opened_at\":0,\"credit_limit\":0}}"}}
{"remove":{"path":"part-00003-f550b5d3-b5b0-4f92-b527-7f91048939c4-c000.snappy.parquet","deletionTimestamp":1754807051323,"dataChange":true,"extendedFileMetadata":true,"partitionValues":{},"size":1865}}
{"remove":{"path":"part-00007-525922bf-f645-49f7-914f-8eb5d4b815ad-c000.snappy.parquet","deletionTimestamp":1754807051323,"dataChange":true,"extendedFileMetadata":true,"partitionValues":{},"size":1837}}
{"remove":{"path":"part-00009-ad85ce87-2935-4f6e-a7c5-59f4fd722ff3-c000.snappy.parquet","deletionTimestamp":1754807051323,"dataChange":true,"extendedFileMetadata":true,"partitionValues":{},"size":1865}}
{"remove":{"path":"part-00001-3280c3ce-11fc-451d-ad87-0365a08f426b-c000.snappy.parquet","deletionTimestamp":1754807051323,"dataChange":true,"extendedFileMetadata":true,"partitionValues":{},"size":1857}}
{"remove":{"path":"part-00005-dd188e35-9c65-4bb8-a378-17ca61236c95-c000.snappy.parquet","deletionTimestamp":1754807051323,"dataChange":true,"extendedFileMetadata":true,"partitionValues":{},"size":1872}}
{"remove":{"path":"part-00011-bbadd9a6-beab-49de-9128-807cb732f9bd-c000.snappy.parquet","deletionTimestamp":1754807051323,"dataChange":true,"extendedFileMetadata":true,"partitionValues":{},"size":1858}}
