{"commitInfo":{"timestamp":1755054923847,"operation":"WRITE","operationParameters":{"mode":"Overwrite","partitionBy":"[]"},"readVersion":51,"isolationLevel":"Serializable","isBlindAppend":false,"operationMetrics":{"numFiles":"7","numOutputRows":"6","numOutputBytes":"13191"},"engineInfo":"Apache-Spark/3.4.4 Delta-Lake/2.4.0","txnId":"dc62f45f-9c7a-4ad0-b37c-255577b9f855"}}
{"add":{"path":"part-00001-ba069c90-1ae7-40ea-96b3-48eba4265d1a-c000.snappy.parquet","partitionValues":{},"size":2056,"modificationTime":1755054923274,"dataChange":true,"stats":"{\"numRecords\":1,\"minValues\":{\"user_id\":\"USER001\",\"age\":25,\"segment\":\"PREMIUM\",\"country\":\"US\",\"city\":\"New York\",\"income_bracket\":\"HIGH\",\"signup_date\":\"2022-12-01\"},\"maxValues\":{\"user_id\":\"USER001\",\"age\":25,\"segment\":\"PREMIUM\",\"country\":\"US\",\"city\":\"New York\",\"income_bracket\":\"HIGH\",\"signup_date\":\"2022-12-01\"},\"nullCount\":{\"user_id\":0,\"age\":0,\"segment\":0,\"country\":0,\"city\":0,\"income_bracket\":0,\"signup_date\":0}}"}}
{"add":{"path":"part-00003-c34a9700-4e0e-47e8-84ec-ba1e352c1374-c000.snappy.parquet","partitionValues":{},"size":2062,"modificationTime":1755054923278,"dataChange":true,"stats":"{\"numRecords\":1,\"minValues\":{\"user_id\":\"USER002\",\"age\":34,\"segment\":\"STANDARD\",\"country\":\"UK\",\"city\":\"London\",\"income_bracket\":\"MEDIUM\",\"signup_date\":\"2023-01-15\"},\"maxValues\":{\"user_id\":\"USER002\",\"age\":34,\"segment\":\"STANDARD\",\"country\":\"UK\",\"city\":\"London\",\"income_bracket\":\"MEDIUM\",\"signup_date\":\"2023-01-15\"},\"nullCount\":{\"user_id\":0,\"age\":0,\"segment\":0,\"country\":0,\"city\":0,\"income_bracket\":0,\"signup_date\":0}}"}}
{"add":{"path":"part-00005-7dcd9d6b-8d9f-47b0-b917-32a73801fd41-c000.snappy.parquet","partitionValues":{},"size":2049,"modificationTime":1755054923263,"dataChange":true,"stats":"{\"numRecords\":1,\"minValues\":{\"user_id\":\"USER003\",\"age\":28,\"segment\":\"PREMIUM\",\"country\":\"CA\",\"city\":\"Toronto\",\"income_bracket\":\"HIGH\",\"signup_date\":\"2023-02-01\"},\"maxValues\":{\"user_id\":\"USER003\",\"age\":28,\"segment\":\"PREMIUM\",\"country\":\"CA\",\"city\":\"Toronto\",\"income_bracket\":\"HIGH\",\"signup_date\":\"2023-02-01\"},\"nullCount\":{\"user_id\":0,\"age\":0,\"segment\":0,\"country\":0,\"city\":0,\"income_bracket\":0,\"signup_date\":0}}"}}
{"add":{"path":"part-00007-79852b22-285f-4e1c-95c5-1fe9f2f278a4-c000.snappy.parquet","partitionValues":{},"size":2104,"modificationTime":1755054923274,"dataChange":true,"stats":"{\"numRecords\":1,\"minValues\":{\"user_id\":\"USER004\",\"age\":45,\"segment\":\"GOLD\",\"country\":\"US\",\"city\":\"San Francisco\",\"income_bracket\":\"VERY_HIGH\",\"signup_date\":\"2022-11-15\"},\"maxValues\":{\"user_id\":\"USER004\",\"age\":45,\"segment\":\"GOLD\",\"country\":\"US\",\"city\":\"San Francisco\",\"income_bracket\":\"VERY_HIGH\",\"signup_date\":\"2022-11-15\"},\"nullCount\":{\"user_id\":0,\"age\":0,\"segment\":0,\"country\":0,\"city\":0,\"income_bracket\":0,\"signup_date\":0}}"}}
{"add":{"path":"part-00009-eb5ee8c7-93d5-44a6-8b90-69b4b0a6d342-c000.snappy.parquet","partitionValues":{},"size":2063,"modificationTime":1755054923269,"dataChange":true,"stats":"{\"numRecords\":1,\"minValues\":{\"user_id\":\"USER005\",\"age\":33,\"segment\":\"STANDARD\",\"country\":\"DE\",\"city\":\"Berlin\",\"income_bracket\":\"MEDIUM\",\"signup_date\":\"2023-04-01\"},\"maxValues\":{\"user_id\":\"USER005\",\"age\":33,\"segment\":\"STANDARD\",\"country\":\"DE\",\"city\":\"Berlin\",\"income_bracket\":\"MEDIUM\",\"signup_date\":\"2023-04-01\"},\"nullCount\":{\"user_id\":0,\"age\":0,\"segment\":0,\"country\":0,\"city\":0,\"income_bracket\":0,\"signup_date\":0}}"}}
{"add":{"path":"part-00011-c91a4b1f-b706-4ed0-adc1-e6873dcb4d85-c000.snappy.parquet","partitionValues":{},"size":2014,"modificationTime":1755054923263,"dataChange":true,"stats":"{\"numRecords\":1,\"minValues\":{\"user_id\":\"USER006\",\"age\":39,\"segment\":\"GOLD\",\"country\":\"FR\",\"city\":\"Paris\",\"income_bracket\":\"HIGH\",\"signup_date\":\"2023-05-20\"},\"maxValues\":{\"user_id\":\"USER006\",\"age\":39,\"segment\":\"GOLD\",\"country\":\"FR\",\"city\":\"Paris\",\"income_bracket\":\"HIGH\",\"signup_date\":\"2023-05-20\"},\"nullCount\":{\"user_id\":0,\"age\":0,\"segment\":0,\"country\":0,\"city\":0,\"income_bracket\":0,\"signup_date\":0}}"}}
{"remove":{"path":"part-00011-d2912c28-18c1-4e02-bf1b-41932693c580-c000.snappy.parquet","deletionTimestamp":1755054923846,"dataChange":true,"extendedFileMetadata":true,"partitionValues":{},"size":2014}}
{"remove":{"path":"part-00005-13773208-3dd4-449e-af6b-a31bdc669b42-c000.snappy.parquet","deletionTimestamp":1755054923846,"dataChange":true,"extendedFileMetadata":true,"partitionValues":{},"size":2049}}
{"remove":{"path":"part-00009-943b8f4e-167a-4a77-990c-8d2e4e227e54-c000.snappy.parquet","deletionTimestamp":1755054923846,"dataChange":true,"extendedFileMetadata":true,"partitionValues":{},"size":2063}}
{"remove":{"path":"part-00007-6e2f2aeb-518c-452c-862d-4c4d15a622e8-c000.snappy.parquet","deletionTimestamp":1755054923846,"dataChange":true,"extendedFileMetadata":true,"partitionValues":{},"size":2104}}
{"remove":{"path":"part-00001-6378c977-d1e0-40da-8250-186886a876eb-c000.snappy.parquet","deletionTimestamp":1755054923846,"dataChange":true,"extendedFileMetadata":true,"partitionValues":{},"size":2056}}
{"remove":{"path":"part-00003-e6a68e9f-9cd6-4bbb-be04-101c98f9f5c8-c000.snappy.parquet","deletionTimestamp":1755054923846,"dataChange":true,"extendedFileMetadata":true,"partitionValues":{},"size":2062}}
