{"commitInfo":{"timestamp":1754793337205,"operation":"WRITE","operationParameters":{"mode":"Overwrite","partitionBy":"[]"},"readVersion":1,"isolationLevel":"Serializable","isBlindAppend":false,"operationMetrics":{"numFiles":"7","numOutputRows":"6","numOutputBytes":"10523"},"engineInfo":"Apache-Spark/3.4.4 Delta-Lake/2.4.0","txnId":"d7314775-8120-4c55-b3d9-2e7d6f6d4649"}}
{"add":{"path":"part-00001-1ea61d9b-c8f2-4803-ba36-a8fd147985c3-c000.snappy.parquet","partitionValues":{},"size":1622,"modificationTime":1754793336791,"dataChange":true,"stats":"{\"numRecords\":1,\"minValues\":{\"account_id\":\"ACC001\",\"credit_score\":750,\"fraud_score\":0.05,\"risk_category\":\"LOW\",\"last_risk_assessment\":\"2024-01-10\"},\"maxValues\":{\"account_id\":\"ACC001\",\"credit_score\":750,\"fraud_score\":0.05,\"risk_category\":\"LOW\",\"last_risk_assessment\":\"2024-01-10\"},\"nullCount\":{\"account_id\":0,\"credit_score\":0,\"fraud_score\":0,\"risk_category\":0,\"last_risk_assessment\":0}}"}}
{"add":{"path":"part-00003-e9b89820-6daf-4a33-b329-0f02b2d6e039-c000.snappy.parquet","partitionValues":{},"size":1643,"modificationTime":1754793336790,"dataChange":true,"stats":"{\"numRecords\":1,\"minValues\":{\"account_id\":\"ACC002\",\"credit_score\":680,\"fraud_score\":0.12,\"risk_category\":\"MEDIUM\",\"last_risk_assessment\":\"2024-01-12\"},\"maxValues\":{\"account_id\":\"ACC002\",\"credit_score\":680,\"fraud_score\":0.12,\"risk_category\":\"MEDIUM\",\"last_risk_assessment\":\"2024-01-12\"},\"nullCount\":{\"account_id\":0,\"credit_score\":0,\"fraud_score\":0,\"risk_category\":0,\"last_risk_assessment\":0}}"}}
{"add":{"path":"part-00005-6416cf60-795e-4a83-b594-9af2b5222443-c000.snappy.parquet","partitionValues":{},"size":1621,"modificationTime":1754793336777,"dataChange":true,"stats":"{\"numRecords\":1,\"minValues\":{\"account_id\":\"ACC003\",\"credit_score\":720,\"fraud_score\":0.03,\"risk_category\":\"LOW\",\"last_risk_assessment\":\"2023-12-15\"},\"maxValues\":{\"account_id\":\"ACC003\",\"credit_score\":720,\"fraud_score\":0.03,\"risk_category\":\"LOW\",\"last_risk_assessment\":\"2023-12-15\"},\"nullCount\":{\"account_id\":0,\"credit_score\":0,\"fraud_score\":0,\"risk_category\":0,\"last_risk_assessment\":0}}"}}
{"add":{"path":"part-00007-d816c179-1e58-45b4-96fd-f7698ca9337e-c000.snappy.parquet","partitionValues":{},"size":1657,"modificationTime":1754793336790,"dataChange":true,"stats":"{\"numRecords\":1,\"minValues\":{\"account_id\":\"ACC004\",\"credit_score\":800,\"fraud_score\":0.01,\"risk_category\":\"VERY_LOW\",\"last_risk_assessment\":\"2024-01-14\"},\"maxValues\":{\"account_id\":\"ACC004\",\"credit_score\":800,\"fraud_score\":0.01,\"risk_category\":\"VERY_LOW\",\"last_risk_assessment\":\"2024-01-14\"},\"nullCount\":{\"account_id\":0,\"credit_score\":0,\"fraud_score\":0,\"risk_category\":0,\"last_risk_assessment\":0}}"}}
{"add":{"path":"part-00009-6f66b898-ff1f-40e4-b14d-c9eb4e276c01-c000.snappy.parquet","partitionValues":{},"size":1643,"modificationTime":1754793336786,"dataChange":true,"stats":"{\"numRecords\":1,\"minValues\":{\"account_id\":\"ACC005\",\"credit_score\":650,\"fraud_score\":0.08,\"risk_category\":\"MEDIUM\",\"last_risk_assessment\":\"2024-01-11\"},\"maxValues\":{\"account_id\":\"ACC005\",\"credit_score\":650,\"fraud_score\":0.08,\"risk_category\":\"MEDIUM\",\"last_risk_assessment\":\"2024-01-11\"},\"nullCount\":{\"account_id\":0,\"credit_score\":0,\"fraud_score\":0,\"risk_category\":0,\"last_risk_assessment\":0}}"}}
{"add":{"path":"part-00011-b0747c76-81b5-4059-a1b6-1d2f57b3cae0-c000.snappy.parquet","partitionValues":{},"size":1622,"modificationTime":1754793336786,"dataChange":true,"stats":"{\"numRecords\":1,\"minValues\":{\"account_id\":\"ACC006\",\"credit_score\":780,\"fraud_score\":0.02,\"risk_category\":\"LOW\",\"last_risk_assessment\":\"2024-01-09\"},\"maxValues\":{\"account_id\":\"ACC006\",\"credit_score\":780,\"fraud_score\":0.02,\"risk_category\":\"LOW\",\"last_risk_assessment\":\"2024-01-09\"},\"nullCount\":{\"account_id\":0,\"credit_score\":0,\"fraud_score\":0,\"risk_category\":0,\"last_risk_assessment\":0}}"}}
{"remove":{"path":"part-00001-0b006d19-96de-4244-87fd-e8993546863d-c000.snappy.parquet","deletionTimestamp":1754793337204,"dataChange":true,"extendedFileMetadata":true,"partitionValues":{},"size":1622}}
{"remove":{"path":"part-00007-fd2d4621-a330-4e90-8bf1-00f725a7eddb-c000.snappy.parquet","deletionTimestamp":1754793337204,"dataChange":true,"extendedFileMetadata":true,"partitionValues":{},"size":1657}}
{"remove":{"path":"part-00009-904cfa2e-d532-4d8e-a362-e884118db576-c000.snappy.parquet","deletionTimestamp":1754793337204,"dataChange":true,"extendedFileMetadata":true,"partitionValues":{},"size":1643}}
{"remove":{"path":"part-00005-4ce40d29-a59e-4c04-8aca-d560fc462446-c000.snappy.parquet","deletionTimestamp":1754793337204,"dataChange":true,"extendedFileMetadata":true,"partitionValues":{},"size":1621}}
{"remove":{"path":"part-00003-bbe4cf8e-fbf9-445b-8a81-11e0150d6648-c000.snappy.parquet","deletionTimestamp":1754793337204,"dataChange":true,"extendedFileMetadata":true,"partitionValues":{},"size":1643}}
{"remove":{"path":"part-00011-89d293d3-2f40-48d9-917b-f1055edf8243-c000.snappy.parquet","deletionTimestamp":1754793337204,"dataChange":true,"extendedFileMetadata":true,"partitionValues":{},"size":1622}}
